{"Total Initial Vulnerabilities": 824, "Initial Vulns Per OS": {"centos": {"6": 43, "5": 14, "7": 22, "4": 60, "8": 14, "3": 34}, "ubuntu": {"18.04": 36, "20.04": 13, "16.04": 8, "12.04": 33, "14.04": 18, "10.04": 56}, "freebsd": {"8": 189, "10": 13, "13": 25, "12": 19, "11": 34, "9": 10}, "windows": {"8": 23, "xp": 58, "vista": 60, "7": 11, "8.1": 19, "10": 12}}, "Average Initial RoA Per OS": {"centos": {"6": 0.06181598470130038, "5": 0.07185041181612253, "7": 0.03968769463814216, "4": 0.06168962660613942, "8": 0.05526595706301962, "3": 0.040296281664114066}, "ubuntu": {"18.04": 0.025571044139387843, "20.04": 0.029001358750251702, "16.04": 0.030016368280935554, "12.04": 0.07315747926060924, "14.04": 0.04861140115280208, "10.04": 0.06117917372491793}, "freebsd": {"8": 0.050053722606422, "10": 0.022068584261066615, "13": 0.04585063065094331, "12": 0.020748276824452343, "11": 0.06298660207810126, "9": 0.017204266393083527}, "windows": {"8": 0.07466082512600028, "xp": 0.03994720097948788, "vista": 0.07252683248808836, "7": 0.05305023569290615, "8.1": 0.038283903837779854, "10": 0.00764534721390547}}, "OS Types In Initial Network": {"centos 6": 12, "ubuntu 18.04": 11, "freebsd 8": 6, "freebsd 10": 5, "windows 8": 13, "freebsd 13": 21, "ubuntu 20.04": 9, "freebsd 12": 10, "centos 5": 5, "centos 7": 10, "ubuntu 16.04": 5, "centos 4": 8, "windows xp": 2, "ubuntu 14.04": 8, "ubuntu 12.04": 5, "centos 8": 14, "windows 10": 11, "windows vista": 10, "freebsd 11": 10, "windows 7": 3, "windows 8.1": 16, "freebsd 9": 3, "ubuntu 10.04": 2, "centos 3": 1}, "Initial Hosts Without Vulnerabilities": 47, "Host Compromises": {"record name": "Host Compromises", "x": [767, 4882, 9678, 10904, 12243, 14498, 17250, 17441, 17726, 18299, 19782, 20074, 20895, 22013, 22924, 24176, 25465, 45341, 51527, 52977, 65633, 66949, 67312, 70469, 71493, 74935, 82613, 86564, 90346, 91599, 100139, 106963, 118330, 130468, 132750, 132853, 149101, 165405, 186063, 212317, 214404, 244742], "y": ["freebsd 8", "freebsd 8", "freebsd 8", "centos 4", "freebsd 10", "centos 4", "windows vista", "freebsd 11", "centos 6", "centos 6", "ubuntu 18.04", "centos 4", "windows vista", "windows 8.1", "windows vista", "freebsd 13", "freebsd 12", "windows vista", "windows vista", "windows 10", "ubuntu 16.04", "ubuntu 18.04", "freebsd 13", "windows vista", "freebsd 8", "ubuntu 18.04", "freebsd 8", "freebsd 8", "windows 10", "freebsd 10", "centos 7", "ubuntu 10.04", "ubuntu 12.04", "windows 8", "freebsd 13", "freebsd 13", "ubuntu 14.04", "ubuntu 10.04", "freebsd 12", "windows xp", "centos 7", "ubuntu 14.04"], "cumulative y": [0, 1, 2, 3, 4, 5, 6, 7, 8, 9, 10, 11, 12, 13, 14, 15, 16, 17, 18, 19, 20, 21, 22, 23, 24, 25, 26, 27, 28, 29, 30, 31, 32, 33, 34, 35, 36, 37, 38, 39, 40, 41], "total events": 42}, "Vuln Compromises": {"record name": "Vuln Compromises", "x": [767, 4882, 9678, 10904, 12243, 14498, 17250, 17726, 18299, 19782, 20074, 22013, 22924, 25465, 45341, 51527, 66949, 70469, 71493, 82613, 86564, 106963, 118330, 149101, 165405, 186063, 212317, 214404, 244742], "y": ["freebsd 8", "freebsd 8", "freebsd 8", "centos 4", "freebsd 10", "centos 4", "windows vista", "centos 6", "centos 6", "ubuntu 18.04", "centos 4", "windows 8.1", "windows vista", "freebsd 12", "windows vista", "windows vista", "ubuntu 18.04", "windows vista", "freebsd 8", "freebsd 8", "freebsd 8", "ubuntu 10.04", "ubuntu 12.04", "ubuntu 14.04", "ubuntu 10.04", "freebsd 12", "windows xp", "centos 7", "ubuntu 14.04"], "cumulative y": [0, 1, 2, 3, 4, 5, 6, 7, 8, 9, 10, 11, 12, 13, 14, 15, 16, 17, 18, 19, 20, 21, 22, 23, 24, 25, 26, 27, 28], "total events": 29}, "Reuse Password Compromises": {"record name": "Reuse Password Compromises", "x": [17441, 20895, 24176, 52977, 67312, 74935, 90346, 91599, 132750, 132853], "y": ["freebsd 11", "windows vista", "freebsd 13", "windows 10", "freebsd 13", "ubuntu 18.04", "windows 10", "freebsd 10", "freebsd 13", "freebsd 13"], "cumulative y": [0, 1, 2, 3, 4, 5, 6, 7, 8, 9], "total events": 10}, "Password Spray Compromises": {"record name": "Password Spray Compromises", "x": [65633, 100139, 130468], "y": ["ubuntu 16.04", "centos 7", "windows 8"], "cumulative y": [0, 1, 2], "total events": 3}, "User Account Leaks": {"record name": "User Account Has Been Leaked By Compromise", "x": [767, 767, 767, 4882, 4882, 4882, 9678, 9678, 9678, 10904, 10904, 10904, 12243, 12243, 12243, 14498, 17250, 17250, 17250, 17441, 17441, 18299, 19782, 20074, 20074, 20895, 22013, 22013, 22924, 25465, 25465, 51527, 52977, 52977, 65633, 67312, 70469, 70469, 71493, 74935, 82613, 82613, 86564, 106963, 106963, 106963, 118330, 118330, 130468, 130468, 149101, 212317, 244742], "y": ["Goldie", "Danielle", "Addia", "Beatrisa", "Nicol", "Meghann", "Starr", "Betti", "Julia", "Eba", "Delia", "Flossie", "Kai", "Ora", "Peg", "Natassia", "Odessa", "Bernete", "Sophie", "Abra", "Melloney", "Felisha", "Sharron", "Sarette", "Alyda", "Darcee", "Karlotta", "Ronnica", "Kandace", "Di", "Helaine", "Nicky", "Anestassia", "Rycca", "Rhodia", "Hillary", "Jerrilee", "Sela", "Hayley", "Clari", "Elinor", "Tabina", "Carolynn", "Gertie", "Tiertza", "Devi", "Karita", "Theadora", "Ramona", "Dode", "Rheta", "Silvana", "Natalie"], "cumulative y": [0, 1, 2, 3, 4, 5, 6, 7, 8, 9, 10, 11, 12, 13, 14, 15, 16, 17, 18, 19, 20, 21, 22, 23, 24, 25, 26, 27, 28, 29, 30, 31, 32, 33, 34, 35, 36, 37, 38, 39, 40, 41, 42, 43, 44, 45, 46, 47, 48, 49, 50, 51, 52], "total events": 53}, "Vulnerabilities Exploited": {"record name": "Vulnerabilities Exploited", "x": [321, 767, 767, 767, 1158, 1158, 1267, 1616, 1616, 2012, 2256, 2320, 2382, 2450, 2539, 2539, 2818, 2818, 2818, 3333, 3333, 3556, 3850, 4882, 4882, 4882, 4882, 4882, 4882, 4882, 4882, 4882, 4882, 4999, 5579, 5579, 5579, 5579, 5579, 5579, 5742, 6103, 6824, 6824, 6824, 6824, 7059, 7530, 9678, 9678, 9678, 9678, 9678, 9678, 9678, 9678, 9678, 9678, 9678, 9678, 9678, 9862, 10904, 10904, 10904, 10904, 11104, 11104, 11104, 11649, 11943, 11943, 12243, 12243, 12303, 15587, 15587, 16282, 17250, 17250, 17726, 17726, 18299, 18299, 18299, 18299, 19087, 19087, 19087, 19782, 20074, 20074, 20074, 20394, 22213, 22213, 22213, 22924, 25269, 29383, 31391, 31391, 32690, 36248, 37982, 38310, 39569, 40058, 41219, 41536, 44911, 44911, 44911, 45341, 48542, 50519, 52134, 52727, 52727, 52727, 52727, 55923, 65792, 66949, 67068, 67538, 67538, 68615, 70469, 71493, 71493, 71493, 71493, 71493, 71493, 72478, 74210, 79039, 82613, 82613, 82613, 82613, 82613, 82613, 82613, 82613, 82613, 82613, 82613, 82613, 82613, 82613, 82613, 82613, 82613, 82613, 82613, 84045, 86564, 86564, 86564, 86564, 86564, 86564, 86564, 86564, 86564, 86564, 86564, 86564, 86713, 87123, 87780, 88719, 89741, 90058, 90683, 90683, 94562, 102878, 106963, 106963, 106963, 106963, 106963, 106963, 106963, 106963, 106963, 106963, 106963, 106963, 106963, 106963, 110788, 113988, 117519, 118330, 118330, 118330, 125720, 132012, 134322, 136076, 141991, 141991, 144520, 144520, 149101, 151494, 165405, 165405, 165405, 165602, 172259, 177256, 185716, 212317, 212317, 212317, 212317, 217761, 218296, 223048, 235204], "cumulative exploited vulns": [0, 1, 2, 3, 4, 5, 6, 7, 8, 9, 10, 11, 12, 13, 14, 15, 16, 17, 18, 19, 20, 21, 22, 23, 24, 25, 26, 27, 28, 29, 30, 31, 32, 33, 34, 35, 36, 37, 38, 39, 40, 41, 42, 43, 44, 45, 46, 47, 48, 49, 50, 51, 52, 53, 54, 55, 56, 57, 58, 59, 60, 61, 62, 63, 64, 65, 66, 67, 68, 69, 70, 71, 72, 73, 74, 75, 76, 77, 78, 79, 80, 81, 82, 83, 84, 85, 86, 87, 88, 89, 90, 91, 92, 93, 94, 95, 96, 97, 98, 99, 100, 101, 102, 103, 104, 105, 106, 107, 108, 109, 110, 111, 112, 113, 114, 115, 116, 117, 118, 119, 120, 121, 122, 123, 124, 125, 126, 127, 128, 129, 130, 131, 132, 133, 134, 135, 136, 137, 138, 139, 140, 141, 142, 143, 144, 145, 146, 147, 148, 149, 150, 151, 152, 153, 154, 155, 156, 157, 158, 159, 160, 161, 162, 163, 164, 165, 166, 167, 168, 169, 170, 171, 172, 173, 174, 175, 176, 177, 178, 179, 180, 181, 182, 183, 184, 185, 186, 187, 188, 189, 190, 191, 192, 193, 194, 195, 196, 197, 198, 199, 200, 201, 202, 203, 204, 205, 206, 207, 208, 209, 210, 211, 212, 213, 214, 215, 216, 217, 218, 219, 220, 221, 222, 223, 224], "roa": [0.11189797015632943, 0.73824825508946, 0.20865587488369428, 0.09077758588482086, 0.2977741040399592, 0.1085031160156252, 0.09535092025842969, 0.6490766033505768, 0.3046316837211133, 0.05602215197372919, 0.383056334179574, 0.393519889083067, 0.016660221333121464, 0.47548927334515, 0.2801545476632342, 0.04576894087994011, 0.3755567818013442, 0.28394839676536654, 0.11450893862193559, 0.42428318875985777, 0.6840198303291107, 0.635127288038632, 0.24997478388507174, 0.43605618185524725, 0.050359677955607265, 0.1901084730486631, 0.32795670002444793, 0.2676610874236006, 0.375076117315914, 0.30777226222044773, 0.28926192092134523, 0.14724797852566235, 0.48815779841313367, 0.19116772624728942, 0.45727131126193116, 0.0502677334594824, 0.6162485527590333, 0.35593659999948296, 0.04236077163903201, 0.0782780712257534, 0.6086651159530039, 0.3054163326562821, 0.6750476408154701, 0.1076428332356421, 0.052915290189955846, 0.006101243966051901, 0.6591765980421764, 0.7832699916406548, 0.39238600611297675, 0.33479347095556633, 0.214646478160388, 0.6715122952954763, 0.35537510324726473, 0.5608449452986295, 0.22960929538892452, 0.2927730291606573, 0.08486259992925596, 0.08621624825179809, 0.568755305758455, 0.6776319934549183, 0.005776068993378321, 0.45900122225571616, 0.8957085647569937, 0.347168927285882, 0.3789560622383604, 0.08768182420640033, 0.32980075579702195, 0.32980075579702195, 0.10370032757935854, 0.036102068862959656, 0.1137789603676826, 0.11462645852094103, 0.43211249728359613, 0.2224961638377287, 0.41388542594616434, 0.4744739704115661, 0.0048802387028202745, 0.08410272770963469, 0.17364752733305994, 0.23554702641744446, 0.6044099581916381, 0.04566337707266929, 0.5167292144114668, 0.1180211024560176, 0.3984807089737582, 0.3984807089737582, 0.21282755574210738, 0.04150903638043159, 0.006511552688931945, 0.21725080867031613, 0.09098841139260475, 0.5521906822613283, 0.05494114291384329, 0.27884353393108186, 0.19160466363142456, 0.201605530885624, 0.015826186887560524, 0.8351794711429023, 0.2449937661895282, 0.0014965653839073138, 0.5785417781112648, 0.04845141874150194, 0.04231475698046741, 0.08815897426457084, 0.20588072422517162, 0.2830199861649359, 0.21122838552864795, 0.155513701273322, 0.5808417893824636, 0.06422760306794337, 0.1940964928442163, 0.1940964928442163, 0.1940964928442163, 0.3273309311962131, 0.11680749331607465, 0.3224314352107505, 0.08698985660647121, 0.16813615461848125, 0.13992986773846047, 0.13992986773846047, 0.13992986773846047, 0.37546954674399224, 0.5386413954528357, 0.13774336764092673, 0.3355020448499286, 0.45082928489713414, 0.1717753653386302, 0.13424144443901131, 0.2456022147471419, 0.8842045264120848, 0.7800695510511589, 0.8082449275513458, 0.15827773260813086, 0.27022029138555387, 0.04011798368283538, 0.13983257272672894, 0.14578977140671803, 0.056850471479437156, 0.8457357599437053, 0.09119554092737928, 0.5951317580340185, 0.2466206246787984, 0.4601767907495916, 0.4718187221029216, 0.18156513278862366, 0.2534474105493857, 0.1883407288440577, 0.4601767907495916, 0.18156513278862366, 0.2466206246787984, 0.3419918243005979, 0.3954791614607823, 0.6080720951525557, 0.0039272932017505, 0.20800857409220094, 0.11543229707387696, 0.056350378130351333, 0.4926746328514269, 0.7718861550424616, 0.3286281207983611, 0.13444769659490152, 0.2813165404849192, 0.21275197719626743, 0.6526203852165186, 0.1763986480355529, 0.18966806682292225, 0.0525019617379733, 0.1763986480355529, 0.18966806682292225, 0.0525019617379733, 0.0551231967703776, 0.29747938070471563, 0.7663193653141664, 0.9095899147156234, 0.17777513202360734, 0.5010030903756819, 0.26538854467869566, 0.1675909956584416, 0.6117197218490014, 0.20903958247618157, 0.3090300198232311, 0.3075662247383123, 0.20012703031493398, 0.19725630998292523, 0.06970792117391554, 0.04233231065423741, 0.10905454733566664, 0.4293946097638841, 0.6065879081148073, 0.2246449494402008, 0.23597782079926893, 0.5341269861135074, 0.20012703031493398, 0.19725630998292523, 0.13388246079963878, 0.174997584066985, 0.04696134045866137, 0.6104024964149865, 0.12050232352409926, 0.4353759104849506, 0.33670822226802416, 0.09467894059509908, 0.03964472153308223, 0.05850116313600475, 0.15333806418883025, 0.15333806418883025, 0.26014726106542857, 0.26014726106542857, 0.8047015116673808, 0.14763766534737596, 0.14200963004440542, 0.6415980283619883, 0.2552097023694208, 0.381363197779, 0.2995857490847612, 0.008552324697527593, 0.015228058189882154, 0.1982292416260802, 0.0504429084680185, 0.09723959634345938, 0.015781122938985266, 0.22625824163647995, 0.044090426643980406, 0.022987487121314782, 0.12663448794338253], "impact": [1.3376683750386276, 7.493927115152036, 3.0266169364850803, 1.1718813818868312, 3.763290898240188, 3.913030526632597, 4.217246305699502, 8.770042688206203, 4.5370647395227115, 1.5781419375575834, 3.8916960302914196, 4.709487393011428, 0.46879197871759537, 6.736560035883208, 3.5583978704386334, 1.163487659451271, 5.005422169208687, 4.817223569117319, 2.1424864032146473, 5.770173163685821, 8.87134576996068, 6.85216111249236, 3.5437800918743023, 5.089440035884827, 0.5138886052727287, 2.654295184964679, 7.534230959675812, 6.291782032618496, 5.144932178127167, 4.921939787153643, 6.030036347919571, 1.6035093405267875, 8.173697551209168, 2.8631491825241, 5.214679631118747, 1.0550800680099415, 8.717450157751326, 9.460177426997419, 0.5389759095259417, 2.6601636922784335, 6.394585465422072, 3.2018510644797313, 8.187549579130426, 1.4021609386475609, 5.2469930869152, 0.06711348571216025, 7.3570262714848855, 8.9218127831238, 4.023731140328554, 4.385706285373779, 4.968066338440499, 7.7537337377432625, 9.242090578826199, 6.267592429741705, 2.3595766619364844, 6.341174609572149, 1.3296067750181573, 2.273001664905152, 6.10665397904854, 8.07889151759621, 0.19299327957889134, 4.648722992336721, 9.123625293653806, 3.874119486219789, 6.67232597273931, 1.4212517565322258, 8.342172459020583, 8.342172459020583, 1.5316738112422856, 1.5886366265852059, 5.1744914845786285, 1.6283555370876468, 7.890463294427034, 4.211078965139369, 5.029314475017976, 6.975974163020218, 0.09698075546289875, 2.271672007454708, 4.033010857138315, 9.91704670742785, 8.750000814373678, 1.325677528030439, 6.842533358139887, 7.903625602778771, 7.005994525520336, 7.005994525520336, 7.155020297424086, 0.9496077950441473, 0.21791602982254243, 7.479080896907821, 4.816653129182292, 8.141376218107244, 1.8815047884748404, 6.048279351546295, 2.396776726954599, 3.405373349617611, 0.3315539308994131, 8.834918000181053, 5.954450891373718, 0.031647279557255326, 7.017125019041243, 0.809752168038459, 5.96809098354711, 3.229239364690788, 3.126841542710479, 5.33147294861681, 2.676395764554532, 2.411233261921865, 6.278333131392738, 2.2211876567382403, 2.8240494724524376, 2.8240494724524376, 2.8240494724524376, 8.805121664549336, 1.580015033597043, 6.445181456140814, 1.3854353506866712, 3.308488017448703, 5.779567730807198, 5.779567730807198, 5.779567730807198, 6.688018287763271, 6.253922712320298, 4.573495625417473, 3.982728340274373, 9.053258129163293, 3.979252588366924, 2.7531324359018186, 3.802395909654476, 9.578965590562627, 9.611379071601304, 8.827263042505319, 2.020761614534665, 4.75419677178256, 3.349229015520685, 4.472181683723242, 2.9103537431546656, 4.287162802663813, 9.948367815582909, 1.738845063850336, 7.366155814583538, 3.1290445045983937, 7.819975299957643, 8.44018624040502, 2.8089589708531317, 7.015643142075177, 6.320828886106301, 7.819975299957643, 2.8089589708531317, 3.1290445045983937, 6.294368700004486, 4.276685920530828, 8.398689688313478, 0.04747855823947322, 4.4331425384804355, 6.878604031639083, 0.8296104584116137, 6.706622019581518, 8.254959012363063, 3.5973740947006636, 3.4360944029884575, 4.434073811528671, 5.987640602177704, 7.204100977040247, 2.3730974158581954, 3.3850709248452535, 0.6408100746065026, 2.3730974158581954, 3.3850709248452535, 0.6408100746065026, 0.9715669590475773, 6.5226973893167886, 8.262912312445883, 9.144413358354216, 5.514094801885038, 5.482789872671104, 6.505904482115725, 2.204072640879029, 6.794852336906578, 4.315128635537203, 5.471223671483409, 7.687303490951022, 3.533683562882173, 6.07051417723354, 1.8157956679764764, 3.3852708245428698, 2.504141779476737, 4.3092595273679795, 6.83948323094379, 3.658744897669343, 2.476719172625689, 6.865937702423503, 3.533683562882173, 6.07051417723354, 4.865689783100597, 8.611077061695614, 1.399685155218754, 6.898154474926096, 6.537039041667096, 9.282755079083739, 6.623584728664254, 5.624489347948101, 1.4962148149511612, 7.952348817705182, 6.92759919385546, 6.92759919385546, 4.976803767466644, 4.976803767466644, 9.970527173513501, 6.49967612222741, 6.544888683593236, 7.421705558643175, 7.62441172194288, 8.213896801145392, 5.822880628744857, 0.2769480177126893, 6.564555979383191, 4.497779515192235, 1.2785049080223043, 3.160969927915047, 0.35036263404912393, 5.0034352230864645, 6.321691118624945, 4.820337235192853, 4.6114188921627886], "complexity": [0.8365150305141823, 0.9851286831930745, 0.6894029844622951, 0.7746311810045231, 0.7912598629545381, 0.27728665870899505, 0.2260975844108638, 0.7401065495649678, 0.6714289991664519, 0.354988044107313, 0.9842915047784188, 0.8355896432954143, 0.3553862286359156, 0.7058339431585132, 0.7873052926167032, 0.39337710639342616, 0.7502999129855942, 0.5894440909608761, 0.5344675161070946, 0.7353040831253629, 0.7710440423202471, 0.9269006925139492, 0.7053902257034812, 0.8567861666129966, 0.9799726524171632, 0.7162295818699339, 0.4352888858593731, 0.42541379538573465, 0.7290205280265665, 0.6253068414687625, 0.47970178657570406, 0.9182857549011109, 0.5972300728706539, 0.6676834284923968, 0.8768924336849991, 0.4764352486944029, 0.7069137667636464, 0.37624727733299423, 0.7859492584054563, 0.29426035492841474, 0.9518445241592047, 0.9538742636859944, 0.8244806755566112, 0.7676924258029026, 0.10084878960849875, 0.909093589955859, 0.8959823897830573, 0.877926953502389, 0.975179484981536, 0.7633741276110856, 0.4320523590829639, 0.8660502385150527, 0.38451809167661233, 0.894833146197004, 0.9730952975288631, 0.4617015729526036, 0.6382533657599411, 0.3793056977606557, 0.9313697938507909, 0.8387685265719976, 0.2992886076645582, 0.9873705596404988, 0.981746329915619, 0.8961234379083015, 0.5679519612600413, 0.6169337965874465, 0.39534157009712834, 0.39534157009712834, 0.6770392417642169, 0.22725189800364543, 0.21988433202909774, 0.7039399928958586, 0.5476389423024037, 0.5283590397606448, 0.8229460058663065, 0.6801544262115568, 0.5032172289776886, 0.3702239030707055, 0.430565484409021, 0.2375173107141062, 0.6907541736439273, 0.34445312760571145, 0.7551723716432671, 0.14932526967689808, 0.5687710824241088, 0.5687710824241088, 0.2974520642781803, 0.43711768792401107, 0.2988101744619043, 0.2904779499846527, 0.18890380717129107, 0.6782522603895892, 0.29200639429878317, 0.46102952215623616, 0.7994264191428542, 0.5920218143137294, 0.47733371293860116, 0.9453166074951539, 0.4114464467990717, 0.47288910922020067, 0.8244712421987197, 0.5983487374769307, 0.07090166201742087, 0.2730022903489918, 0.6584303087092335, 0.5308476454679606, 0.7892270206301327, 0.644955026662872, 0.9251528665756127, 0.28915883299234624, 0.6872984865794883, 0.6872984865794883, 0.6872984865794883, 0.3717506056890658, 0.7392808981706467, 0.5002674283181672, 0.6278882415073063, 0.5081963535359492, 0.24211130357134392, 0.24211130357134392, 0.24211130357134392, 0.5614062799902475, 0.8612856605850056, 0.3011774338985038, 0.8423924912408554, 0.49797462799042047, 0.43167746083976644, 0.4875953030390239, 0.6459143671061328, 0.9230689034766129, 0.8116104309692943, 0.9156234765628474, 0.7832578146263857, 0.5683826403429159, 0.11978274252648702, 0.3126719409358021, 0.5009348837735781, 0.13260628088141024, 0.8501251417533668, 0.5244604181435486, 0.8079271916238518, 0.7881659219495557, 0.588463227949178, 0.5590145864841489, 0.646378728463517, 0.3612604082288281, 0.29796840293849125, 0.588463227949178, 0.646378728463517, 0.7881659219495557, 0.5433298248009434, 0.9247327692740525, 0.7240082890533145, 0.8271719587486096, 0.46921246561925534, 0.16781355132949982, 0.6792390037878828, 0.7346092137188446, 0.9350575258901276, 0.9135222307918082, 0.3912805669075011, 0.6344426196819078, 0.35531854921100237, 0.9059012183427818, 0.7433266197028872, 0.5603075121139236, 0.8193061223360569, 0.7433266197028872, 0.5603075121139236, 0.8193061223360569, 0.5673638472063174, 0.4560680389556976, 0.9274204255561442, 0.9946946611776184, 0.322401297784785, 0.9137740128851654, 0.40791952204067883, 0.7603696563812112, 0.900269338490868, 0.48443418523989756, 0.5648279770281152, 0.4000963733256514, 0.5663411189871927, 0.32494168405487367, 0.3838973867120087, 0.1250485200396153, 0.4354966968302193, 0.9964463895405039, 0.8868914326310927, 0.6139945684196291, 0.9527839224060978, 0.7779374198588694, 0.5663411189871927, 0.32494168405487367, 0.2751561788107336, 0.20322380442444454, 0.33551359949460835, 0.8848779751652721, 0.184337775491346, 0.46901583288129234, 0.5083474222212093, 0.16833339835489136, 0.2649667757391929, 0.07356463414401193, 0.22134372947678005, 0.22134372947678005, 0.5227195469630743, 0.5227195469630743, 0.8070802051520944, 0.22714618785771312, 0.21697791499555363, 0.8644886586948949, 0.33472707361137544, 0.4642902230349675, 0.5144974939136576, 0.30880613510655, 0.02319739253912645, 0.44072689858744196, 0.39454606823565275, 0.307625819166201, 0.4504225452527171, 0.45220579771373204, 0.06974467087466729, 0.04768854542683276, 0.2746106803669489], "total had os dependency": 9, "total were dependent on another vuln": 9}, "MTD Statistics": [{"record name": "PortShuffle", "x": [4843, 10251, 19105, 27987, 35856, 46929, 49670, 54092, 56408, 57810, 60450, 62228, 76588, 95577, 102010, 104642, 113425, 116040, 120640, 123606, 128288, 133184, 136982, 142565, 147008, 152235, 156766, 160727, 162709, 170756, 177363, 193671, 201455, 205584, 208429, 211236, 214775, 230859, 239023, 243791, 247206, 248220], "y": [1, 1, 1, 1, 1, 1, 1, 1, 1, 1, 1, 1, 1, 1, 1, 1, 1, 1, 1, 1, 1, 1, 1, 1, 1, 1, 1, 1, 1, 1, 1, 1, 1, 1, 1, 1, 1, 1, 1, 1, 1, 1], "cumulative y": [0, 1, 2, 3, 4, 5, 6, 7, 8, 9, 10, 11, 12, 13, 14, 15, 16, 17, 18, 19, 20, 21, 22, 23, 24, 25, 26, 27, 28, 29, 30, 31, 32, 33, 34, 35, 36, 37, 38, 39, 40, 41], "total events": 42, "blocked times": [46929, 49670, 54092, 76588, 95577, 102010, 104642, 113425, 116040, 120640, 123606, 128288, 133184, 136982, 142565, 147008, 152235, 156766, 160727, 162709, 170756, 177363, 193671, 201455, 205584, 208429, 211236, 214775, 230859, 239023, 243791, 247206, 248220], "total blocks": 33, "blocked values": ["PortShuffle", "PortShuffle", "PortShuffle", "PortShuffle", "PortShuffle", "PortShuffle", "PortShuffle", "PortShuffle", "PortShuffle", "PortShuffle", "PortShuffle", "PortShuffle", "PortShuffle", "PortShuffle", "PortShuffle", "PortShuffle", "PortShuffle", "PortShuffle", "PortShuffle", "PortShuffle", "PortShuffle", "PortShuffle", "PortShuffle", "PortShuffle", "PortShuffle", "PortShuffle", "PortShuffle", "PortShuffle", "PortShuffle", "PortShuffle", "PortShuffle", "PortShuffle", "PortShuffle"], "cumulative blocked": [0, 1, 2, 3, 4, 5, 6, 7, 8, 9, 10, 11, 12, 13, 14, 15, 16, 17, 18, 19, 20, 21, 22, 23, 24, 25, 26, 27, 28, 29, 30, 31, 32]}, {"record name": "CompleteTopologyShuffle", "x": [7068, 14927, 17673, 23388, 32604, 34806, 40668, 42417, 64279, 67794, 71907, 75290, 78192, 83061, 87213, 91789, 97567, 98709, 107379, 112346, 140305, 143590, 150906, 166616, 174648, 182051, 185209, 187760, 191529, 197681, 202539, 215895, 219323, 223977, 228834, 234724], "y": [1, 1, 1, 1, 1, 1, 1, 1, 1, 1, 1, 1, 1, 1, 1, 1, 1, 1, 1, 1, 1, 1, 1, 1, 1, 1, 1, 1, 1, 1, 1, 1, 1, 1, 1, 1], "cumulative y": [0, 1, 2, 3, 4, 5, 6, 7, 8, 9, 10, 11, 12, 13, 14, 15, 16, 17, 18, 19, 20, 21, 22, 23, 24, 25, 26, 27, 28, 29, 30, 31, 32, 33, 34, 35], "total events": 36, "blocked times": [23388, 40668, 42417, 67794, 71907, 75290, 78192, 83061, 87213, 91789, 97567, 98709, 107379, 112346, 140305, 143590, 150906, 166616, 174648, 182051, 185209, 187760, 191529, 197681, 202539, 215895, 219323, 223977, 228834, 234724], "total blocks": 30, "blocked values": ["CompleteTopologyShuffle", "CompleteTopologyShuffle", "CompleteTopologyShuffle", "CompleteTopologyShuffle", "CompleteTopologyShuffle", "CompleteTopologyShuffle", "CompleteTopologyShuffle", "CompleteTopologyShuffle", "CompleteTopologyShuffle", "CompleteTopologyShuffle", "CompleteTopologyShuffle", "CompleteTopologyShuffle", "CompleteTopologyShuffle", "CompleteTopologyShuffle", "CompleteTopologyShuffle", "CompleteTopologyShuffle", "CompleteTopologyShuffle", "CompleteTopologyShuffle", "CompleteTopologyShuffle", "CompleteTopologyShuffle", "CompleteTopologyShuffle", "CompleteTopologyShuffle", "CompleteTopologyShuffle", "CompleteTopologyShuffle", "CompleteTopologyShuffle", "CompleteTopologyShuffle", "CompleteTopologyShuffle", "CompleteTopologyShuffle", "CompleteTopologyShuffle", "CompleteTopologyShuffle"], "cumulative blocked": [0, 1, 2, 3, 4, 5, 6, 7, 8, 9, 10, 11, 12, 13, 14, 15, 16, 17, 18, 19, 20, 21, 22, 23, 24, 25, 26, 27, 28, 29]}], "Total MTD Events": 78, "Total MTD Blocking Hacker Events": 63, "Complete Time": 249999, "Simulation Type": "CompleteTopologyShuffle,PortShuffle"}