{"Total Initial Vulnerabilities": 928, "Initial Vulns Per OS": {"centos": {"5": 31, "8": 10, "7": 12, "4": 38, "6": 24, "3": 96}, "ubuntu": {"14.04": 53, "16.04": 23, "20.04": 8, "18.04": 24, "10.04": 23, "12.04": 27}, "windows": {"8.1": 41, "10": 16, "8": 44, "7": 30, "vista": 29, "xp": 106}, "freebsd": {"9": 46, "10": 41, "13": 7, "11": 46, "12": 37, "8": 116}}, "Average Initial RoA Per OS": {"centos": {"5": 0.1361121964976832, "8": 0.08343193589333112, "7": 0.050781391576855794, "4": 0.0578371907367816, "6": 0.058752136090217705, "3": 0.05881400775880689}, "ubuntu": {"14.04": 0.044891551375350315, "16.04": 0.05908133304612222, "20.04": 0.14675001847696215, "18.04": 0.10997229192575521, "10.04": 0.045891494073281566, "12.04": 0.05397776633480001}, "windows": {"8.1": 0.04525892991299848, "10": 0.07213748236403635, "8": 0.06437603356447148, "7": 0.07082993476641608, "vista": 0.055233060617619505, "xp": 0.06639931617336392}, "freebsd": {"9": 0.031048399742117025, "10": 0.04040487861437244, "13": 0.03396431310205303, "11": 0.08959185372117319, "12": 0.07174079912563655, "8": 0.05500286122691014}}, "OS Types In Initial Network": {"centos 5": 8, "centos 8": 13, "ubuntu 14.04": 11, "windows 8.1": 14, "ubuntu 20.04": 11, "freebsd 9": 7, "centos 7": 8, "freebsd 10": 9, "freebsd 13": 15, "windows 10": 17, "freebsd 11": 11, "windows 8": 8, "ubuntu 16.04": 6, "centos 4": 7, "windows 7": 8, "freebsd 12": 12, "freebsd 8": 4, "ubuntu 18.04": 8, "windows vista": 5, "centos 6": 6, "windows xp": 4, "centos 3": 3, "ubuntu 10.04": 1, "ubuntu 12.04": 4}, "Initial Hosts Without Vulnerabilities": 35, "Host Compromises": {"record name": "Host Compromises", "x": [1796, 1879, 4870, 5121, 5741, 8235, 10232, 15118, 15201, 19407, 27326, 27395, 31840, 34443, 36058, 39229, 41040, 48533, 53257, 60157, 61471, 68226, 68558, 70533, 70967, 71680, 72066, 79152, 89356, 90629, 91904, 98721, 100697, 103486, 106141, 113396, 117285, 122007, 132144, 132982, 144361, 151607, 164704, 169049, 178309, 191873, 201750, 204993, 210891, 234565], "y": ["freebsd 10", "freebsd 10", "freebsd 11", "freebsd 12", "freebsd 8", "centos 5", "ubuntu 14.04", "freebsd 11", "centos 4", "windows xp", "centos 4", "centos 7", "centos 5", "freebsd 9", "centos 3", "freebsd 11", "windows xp", "ubuntu 16.04", "ubuntu 10.04", "freebsd 10", "windows vista", "freebsd 8", "freebsd 10", "windows 10", "windows 8.1", "windows 8", "ubuntu 12.04", "freebsd 11", "freebsd 8", "windows 7", "freebsd 9", "ubuntu 14.04", "windows xp", "ubuntu 18.04", "freebsd 10", "windows xp", "freebsd 10", "freebsd 13", "centos 6", "freebsd 11", "centos 3", "windows 8.1", "windows 7", "windows 8.1", "ubuntu 14.04", "ubuntu 20.04", "centos 3", "freebsd 11", "freebsd 12", "centos 4"], "cumulative y": [0, 1, 2, 3, 4, 5, 6, 7, 8, 9, 10, 11, 12, 13, 14, 15, 16, 17, 18, 19, 20, 21, 22, 23, 24, 25, 26, 27, 28, 29, 30, 31, 32, 33, 34, 35, 36, 37, 38, 39, 40, 41, 42, 43, 44, 45, 46, 47, 48, 49], "total events": 50}, "Vuln Compromises": {"record name": "Vuln Compromises", "x": [1796, 1879, 4870, 5121, 5741, 8235, 10232, 15118, 15201, 19407, 27326, 27395, 31840, 34443, 36058, 39229, 41040, 48533, 53257, 60157, 61471, 68226, 68558, 70533, 70967, 71680, 72066, 79152, 89356, 90629, 91904, 98721, 100697, 103486, 106141, 113396, 117285, 122007, 132144, 132982, 144361, 151607, 164704, 169049, 178309, 201750, 210891, 234565], "y": ["freebsd 10", "freebsd 10", "freebsd 11", "freebsd 12", "freebsd 8", "centos 5", "ubuntu 14.04", "freebsd 11", "centos 4", "windows xp", "centos 4", "centos 7", "centos 5", "freebsd 9", "centos 3", "freebsd 11", "windows xp", "ubuntu 16.04", "ubuntu 10.04", "freebsd 10", "windows vista", "freebsd 8", "freebsd 10", "windows 10", "windows 8.1", "windows 8", "ubuntu 12.04", "freebsd 11", "freebsd 8", "windows 7", "freebsd 9", "ubuntu 14.04", "windows xp", "ubuntu 18.04", "freebsd 10", "windows xp", "freebsd 10", "freebsd 13", "centos 6", "freebsd 11", "centos 3", "windows 8.1", "windows 7", "windows 8.1", "ubuntu 14.04", "centos 3", "freebsd 12", "centos 4"], "cumulative y": [0, 1, 2, 3, 4, 5, 6, 7, 8, 9, 10, 11, 12, 13, 14, 15, 16, 17, 18, 19, 20, 21, 22, 23, 24, 25, 26, 27, 28, 29, 30, 31, 32, 33, 34, 35, 36, 37, 38, 39, 40, 41, 42, 43, 44, 45, 46, 47], "total events": 48}, "Reuse Password Compromises": {"record name": "Reuse Password Compromises", "x": [], "y": [], "cumulative y": [], "total events": 0}, "Password Spray Compromises": {"record name": "Password Spray Compromises", "x": [191873, 204993], "y": ["ubuntu 20.04", "freebsd 11"], "cumulative y": [0, 1], "total events": 2}, "User Account Leaks": {"record name": "User Account Has Been Leaked By Compromise", "x": [1796, 1796, 1796, 1879, 1879, 1879, 4870, 4870, 5121, 5121, 5121, 5741, 5741, 5741, 8235, 8235, 10232, 10232, 10232, 15118, 15118, 15201, 19407, 27326, 27326, 27326, 27395, 27395, 27395, 31840, 31840, 31840, 34443, 34443, 36058, 39229, 41040, 48533, 53257, 60157, 60157, 68226, 68226, 68226, 68558, 68558, 70533, 70533, 70967, 71680, 90629, 91904, 100697, 117285, 132144, 132982, 144361], "y": ["Keriann", "Bertha", "Silvie", "Devora", "Karry", "Dulcia", "Cornela", "Theo", "Mel", "Torie", "Georgianna", "Hilary", "Dacy", "Briney", "Lynnett", "Cori", "Riane", "Kristin", "Eartha", "Christi", "Karia", "Kanya", "Lizzy", "Ania", "Fanni", "Gill", "Dorette", "Nanci", "Lisetta", "Corabella", "Charmion", "Ashlen", "Trista", "Kaylyn", "Corette", "Arielle", "Desiri", "Vanya", "Fancie", "Jacqui", "Tabina", "Sonnnie", "Dawn", "Kit", "Tanya", "Cybill", "Cathrin", "Emilie", "Gianna", "Mirabelle", "Renie", "Ellie", "Salaidh", "Myrna", "Marna", "Arlyn", "Opaline"], "cumulative y": [0, 1, 2, 3, 4, 5, 6, 7, 8, 9, 10, 11, 12, 13, 14, 15, 16, 17, 18, 19, 20, 21, 22, 23, 24, 25, 26, 27, 28, 29, 30, 31, 32, 33, 34, 35, 36, 37, 38, 39, 40, 41, 42, 43, 44, 45, 46, 47, 48, 49, 50, 51, 52, 53, 54, 55, 56], "total events": 57}, "Vulnerabilities Exploited": {"record name": "Vulnerabilities Exploited", "x": [340, 340, 340, 340, 340, 753, 753, 753, 873, 1148, 1148, 1148, 1796, 2008, 2646, 3023, 3023, 3023, 3362, 3843, 4609, 4870, 4870, 4870, 5121, 5741, 5741, 5741, 5741, 5741, 5741, 5741, 6015, 6245, 6412, 6412, 6867, 7187, 7855, 8002, 8002, 8235, 8235, 8844, 8844, 8844, 8844, 8844, 9101, 9377, 9377, 10232, 10232, 10232, 10560, 10560, 10560, 12707, 13451, 15118, 15118, 15201, 15375, 19407, 19407, 19407, 19407, 19407, 19407, 19407, 19407, 19407, 19407, 19407, 19407, 19407, 19407, 19407, 19407, 20552, 20552, 20552, 20552, 20552, 20552, 20552, 20552, 20552, 21884, 23473, 23473, 23784, 24355, 27068, 27068, 27326, 28476, 31840, 32005, 34443, 34973, 34973, 36058, 36058, 36058, 37683, 38580, 38580, 38580, 38580, 39229, 39229, 42117, 43009, 43009, 48533, 50467, 53257, 53257, 53257, 53257, 53822, 58748, 60157, 60750, 60750, 61471, 62511, 62511, 64653, 64653, 64653, 64653, 65814, 65814, 68226, 68226, 68226, 68226, 68226, 68226, 68226, 68226, 68226, 68226, 69940, 69940, 69940, 70533, 70967, 71145, 71145, 71680, 72066, 74407, 75250, 75250, 79152, 79152, 79152, 79152, 81890, 83848, 89356, 89356, 90012, 90012, 90629, 91904, 91904, 98721, 100697, 100697, 100697, 100697, 100697, 103139, 105435, 105435, 106959, 111364, 111364, 113396, 113396, 113396, 113396, 113396, 115151, 128514, 138972, 141551, 144361, 144361, 144361, 144361, 144361, 144361, 144361, 144361, 144361, 144361, 144361, 144361, 144361, 144361, 144361, 144361, 149022, 149539, 149539, 151607, 159418, 164704, 169049, 188153, 188153, 198827, 201750, 201750, 201750, 201750, 201750, 214853, 221504, 221504], "cumulative exploited vulns": [0, 1, 2, 3, 4, 5, 6, 7, 8, 9, 10, 11, 12, 13, 14, 15, 16, 17, 18, 19, 20, 21, 22, 23, 24, 25, 26, 27, 28, 29, 30, 31, 32, 33, 34, 35, 36, 37, 38, 39, 40, 41, 42, 43, 44, 45, 46, 47, 48, 49, 50, 51, 52, 53, 54, 55, 56, 57, 58, 59, 60, 61, 62, 63, 64, 65, 66, 67, 68, 69, 70, 71, 72, 73, 74, 75, 76, 77, 78, 79, 80, 81, 82, 83, 84, 85, 86, 87, 88, 89, 90, 91, 92, 93, 94, 95, 96, 97, 98, 99, 100, 101, 102, 103, 104, 105, 106, 107, 108, 109, 110, 111, 112, 113, 114, 115, 116, 117, 118, 119, 120, 121, 122, 123, 124, 125, 126, 127, 128, 129, 130, 131, 132, 133, 134, 135, 136, 137, 138, 139, 140, 141, 142, 143, 144, 145, 146, 147, 148, 149, 150, 151, 152, 153, 154, 155, 156, 157, 158, 159, 160, 161, 162, 163, 164, 165, 166, 167, 168, 169, 170, 171, 172, 173, 174, 175, 176, 177, 178, 179, 180, 181, 182, 183, 184, 185, 186, 187, 188, 189, 190, 191, 192, 193, 194, 195, 196, 197, 198, 199, 200, 201, 202, 203, 204, 205, 206, 207, 208, 209, 210, 211, 212, 213, 214, 215, 216, 217, 218, 219, 220, 221, 222, 223, 224], "roa": [0.7783161834483577, 0.3109699684634658, 0.6713238111801965, 0.5469702454614122, 0.31322590303228154, 0.7111900456448589, 0.06269357140077517, 0.18170387962399084, 0.11946885775525581, 0.4843653807467804, 0.19298295073985441, 0.01707966787814458, 0.36357292263549446, 0.598145545143503, 0.8300465341793618, 0.4226153540858493, 0.03927469702282201, 0.33571136699785276, 0.9533302886299065, 0.002374786918487629, 0.18669513711681157, 0.21236899929383335, 0.09059155191248972, 0.24956387529715257, 0.40786302324140056, 0.40070391534122046, 0.18349359649275182, 0.40070391534122046, 0.18349359649275182, 0.6021217407687333, 0.5058717702567957, 0.2756396959839841, 0.11107832376913154, 0.020583765883380397, 0.009832301876306921, 0.0057110133510582615, 0.920981609362341, 0.20870309169690765, 0.22169413779063754, 0.38130622430566763, 0.08356420216518182, 0.5078726420300415, 0.0998930440964434, 0.747417748276239, 0.5258275709430569, 0.3709954003386524, 0.14360853101922172, 0.14344807070469218, 0.39610634375463827, 0.6071443321168211, 0.2885365879033369, 0.5029102873290588, 0.0841411154448847, 0.17090770630320398, 0.577197148371551, 0.20180952340483455, 0.0587883239941433, 0.09274942844276227, 0.3566986778399439, 0.13942470130947332, 0.4223878772092967, 0.7089480964674711, 0.2527469778281176, 0.21418832960218426, 0.2096829575701135, 0.4921767072245345, 0.25445939979844406, 0.31480631824073185, 0.3943850192670641, 0.13610975687897295, 0.32710530846099256, 0.1844893844748548, 0.015926632406960683, 0.04431964541174923, 0.7198901191578646, 0.3761365696426211, 0.19990327939856217, 0.21657524165343878, 0.015926632406960683, 0.830826398406237, 0.5127834063875804, 0.7027969436503704, 0.15152972308561904, 0.08045630942136481, 0.8589438602391045, 0.5102643886888691, 0.12414222483617207, 0.037629062295050086, 0.25150954932630853, 0.44017468797078757, 0.44017468797078757, 0.11506069110279744, 0.37532928263337, 0.42982905403336147, 0.28495206416846014, 0.12802512360340684, 0.04606099167333015, 0.5637956066488731, 0.11145200632745436, 0.1429507560403458, 0.3169629061796049, 0.018479429012038952, 0.7058204879530774, 0.1256265701881735, 0.05598731380108686, 0.42202974032269375, 0.45081625252368046, 0.4669976818715734, 0.07076084728314815, 0.3624455036008637, 0.405248357706426, 0.4470009581068459, 0.043205913863890714, 0.4743057748365856, 0.1656485427228555, 0.04783627953678857, 0.10411683631235194, 0.7520393161392338, 0.2582287260886659, 0.5287890266347952, 0.1920033578905719, 0.38432171926935854, 0.28960681656723525, 0.35501038425305326, 0.07087601781848347, 0.04681621895662802, 0.6278817982485638, 0.666711927194924, 0.1769354479887154, 0.31892575297197534, 0.17390252142961551, 0.09167905394004153, 0.46182117586198873, 0.17010178803704396, 0.1854571925819667, 0.6644754100787937, 0.34158777403833407, 0.10144497863168242, 0.3534001063349056, 0.20251798290731715, 0.7889533300214626, 0.3116606932290018, 0.30044890981980876, 0.23445385884686615, 0.3192411384422332, 0.5455301713306413, 0.5455301713306413, 0.2586170599366656, 0.061734956181226555, 0.17354574762065803, 0.31065919299324973, 0.1808267499320895, 0.04535627395506307, 0.5759458595983598, 0.2592657625112857, 0.054745225631699826, 0.054745225631699826, 0.4507255230966768, 0.38664521370614663, 0.4796808776468054, 0.2671143210781287, 0.08212790441188297, 0.028259918909254795, 0.1254605073126903, 0.016379800560560303, 0.5070788235560688, 0.5070788235560688, 0.4872896631688297, 0.3134530305113588, 0.29417750356177763, 0.6449563976721829, 0.008335607456530968, 0.21198751177323777, 0.22785833884110684, 0.23030936489721038, 0.15598289123344167, 0.2966440268806191, 0.07324251198302187, 0.3738014981986727, 0.01850314887403368, 0.03175924984800965, 0.058532350904982114, 0.6994333324377926, 0.7806117345392491, 0.40002672373880455, 0.2892459504852021, 0.0761525187152515, 0.4609587802657146, 0.26455250277569736, 0.4226859096888861, 0.012260500527638657, 0.4128935252655023, 0.0965845135644023, 0.41140439106237353, 0.13417660934785308, 0.03329290321703659, 0.5211386113965628, 0.47614958812251473, 0.2561173590687406, 0.27958249590544965, 0.036212841852052646, 0.6325493374931127, 0.3620517388608698, 0.048689997099479396, 0.41140439106237353, 0.2873065630558419, 0.2748151672473324, 0.23799369627429773, 0.23690485955555385, 0.18733580899808297, 0.075227962586162, 0.5771936253604133, 0.2555655253573204, 0.717338444171027, 0.18924799638923792, 0.058623344546524084, 0.4716816897345136, 0.910894022451008, 0.6738563080577735, 0.19004559214975283, 0.09962400550494394, 0.027795797322757228, 0.07010346508012745, 0.19050476826701052, 0.14432769791342706], "impact": [7.990494479351339, 3.1953576761596967, 8.050643321846279, 8.775030076394915, 6.767412843463932, 9.792295845338655, 0.8960756889792798, 2.0505788358220665, 2.462290596864025, 7.270706388259562, 5.094598090978906, 0.3841010693122726, 4.274463580781981, 6.251517741028657, 8.592125703020466, 4.651237758175358, 1.8746412167744875, 7.970268233468564, 9.849926835947507, 0.5999573993109908, 2.1091434369551845, 2.1371465281588375, 1.4303518779065194, 7.415201125272601, 7.1431930868459625, 4.133224935904231, 5.313382873455145, 4.133224935904231, 5.313382873455145, 6.587930413293122, 8.6679321478252, 4.315754530608774, 2.8620436941376184, 3.3698840581707943, 0.40590041256595377, 0.12692596009049928, 9.326762491452104, 3.1044276016044403, 7.937379239981096, 4.1522853985384796, 1.5999005301107283, 5.529888859840621, 9.464793331265627, 7.87276269495504, 5.651423823199485, 6.570468642044943, 6.8346563372735805, 4.366249409727956, 6.347850440044061, 9.913919980687654, 6.32519646299788, 9.108992639878068, 2.378160323540759, 2.524808451590631, 7.241214115286216, 2.8366905876176163, 1.7506416449304008, 1.3277860307521105, 8.103531021380585, 1.8527660875331475, 9.05893715798594, 9.633172823314522, 5.328284581842304, 5.775908199594215, 5.74770873253586, 5.545125191911165, 3.175733505884797, 9.211684256144432, 4.561528014302009, 2.0182042557322366, 4.029903588452647, 3.0377342457039838, 0.48830264858357064, 0.47637494912861955, 7.396155145654413, 3.828510313598982, 2.529062876574052, 9.109215462284428, 0.48830264858357064, 8.799774691080765, 7.271063782409501, 7.4593152790623805, 2.5883723176543483, 2.186253877662696, 9.521419484324484, 7.958650950239932, 1.88589266122696, 1.1639235599740028, 2.7741599974003615, 4.914992164682053, 4.914992164682053, 4.15766118115266, 7.824653566796005, 6.456974818248015, 9.22228724315625, 6.100630648939658, 3.2544828222205933, 8.807735835468343, 2.437793817291525, 7.347641337644999, 3.2575034718767117, 0.22465018700827843, 8.759645680736082, 1.4395395718124648, 0.784420675156674, 6.901147837262112, 4.790877570847868, 6.172427308759216, 7.26545598375338, 6.516741806005477, 5.390494087619093, 7.307786310480543, 2.0105542120422317, 9.636344151098282, 5.447309453443406, 6.092693886077321, 2.8386219141583013, 8.957381699611863, 8.056618268867476, 7.666185150842296, 2.1302905327146613, 4.102182308398933, 4.916118970065169, 7.539879683791874, 2.536838948350859, 0.9494112375921682, 7.374637815045423, 8.408861046611802, 3.082365681628989, 8.090848539133631, 5.259965497532359, 4.726473092025403, 5.322773847142617, 2.548275530357269, 4.891682865853481, 9.31806372321781, 6.764714780481643, 3.7401567237518063, 9.373010047945314, 9.577037896529694, 9.693526327552247, 4.089213332518832, 4.771690855527293, 4.390813078113539, 5.162470289093196, 5.664564465073852, 5.664564465073852, 7.658111940309979, 1.6683156939421517, 8.104823265878263, 3.398995101931217, 3.3047313019233346, 2.3309435739278026, 9.58251166268656, 4.93867474142304, 4.0687842046375415, 4.0687842046375415, 5.363446847166028, 5.266799805847745, 6.408652516040622, 9.329237259284977, 2.256938378993797, 1.6780256332264931, 4.356554666185585, 2.1884668856434333, 9.48783545617805, 9.48783545617805, 7.417260099210198, 4.114689186044105, 8.205921916925895, 9.44396064680388, 0.33602689482894244, 3.0781210958416216, 3.5262895075618506, 6.514667837023361, 3.1004807409439747, 5.752016031999264, 5.7502385867632, 5.2013138432445025, 9.117026238019267, 0.4587704213483046, 1.500092934280589, 7.014682694666559, 8.15166811489136, 4.5461188606843015, 5.523847258920373, 1.8917204235463847, 5.525156540616811, 6.830653545899584, 6.1421958088518895, 2.525355731030341, 8.734129371224817, 3.872955541707086, 6.69576504457681, 2.9289065383046653, 0.9210185784262159, 8.462545596448601, 7.190435621658908, 9.166366792004327, 6.380871992749605, 0.47652865369229414, 7.843447756246791, 4.694370810009296, 1.3825345337460104, 6.69576504457681, 4.880518563937847, 6.7768386808944285, 3.0135937243736235, 7.974186464868071, 7.7858489749412385, 8.125921305059396, 6.961589292388326, 9.361345015692713, 8.656443145257004, 7.243434225162572, 4.421908855428663, 9.518829566651773, 9.882781242564052, 9.580765580456674, 2.207853760613089, 1.025874885546313, 0.8788255975966208, 5.69654801483887, 2.2062596441430027, 2.532905865387478], "complexity": [0.9740525889350726, 0.9731929880137908, 0.8338759827534376, 0.6233257786007799, 0.4628443842240241, 0.7262750808161098, 0.6996459358493415, 0.8861101872786408, 0.4851939811954423, 0.6661875131265289, 0.37879916588822327, 0.4446659809806174, 0.850569704863368, 0.9568005241637226, 0.9660549238561166, 0.9086083663279294, 0.2095051398176242, 0.421204603363462, 0.9678551978180268, 0.039582592384307724, 0.8851704148975739, 0.9937035036937327, 0.633351508197274, 0.3365571224313595, 0.570981378051325, 0.9694703810102654, 0.3453423193149848, 0.9694703810102654, 0.3453423193149848, 0.9139770808048798, 0.5836129790006719, 0.6386825154884395, 0.38810841356704473, 0.061081525441422646, 0.2422343405405949, 0.4499484066920795, 0.9874612012543607, 0.6722755962775394, 0.27930395044493994, 0.9183044702078516, 0.522308734777395, 0.9184138323616853, 0.10554170661757678, 0.94937162116571, 0.9304337940193025, 0.5646406984802025, 0.21011814483785551, 0.32853842564534086, 0.6240007503262613, 0.6124160103163432, 0.4561701594428935, 0.5521030779269471, 0.35380758232317144, 0.6769135543551117, 0.7970999602857852, 0.7114259281070322, 0.33581015374783063, 0.6985269184540623, 0.44017685241016546, 0.7525218766018615, 0.46626648341073784, 0.7359445423336033, 0.47434962218314547, 0.3708305641305587, 0.364811383679149, 0.8875844822087822, 0.8012618166068336, 0.3417467528055447, 0.864589712110782, 0.6744102163712372, 0.8116951219336502, 0.6073256234832355, 0.32616313782363027, 0.9303521415812964, 0.9733302033027711, 0.9824619469002679, 0.790424315861049, 0.23775400038580885, 0.32616313782363027, 0.9441450804965974, 0.7052384929260695, 0.9421735338403747, 0.5854247553649442, 0.36800991066682476, 0.9021174433635869, 0.6411443244328815, 0.6582677126247751, 0.3232949618778278, 0.9066151539997538, 0.8955755639526277, 0.8955755639526277, 0.2767437895718532, 0.47967527179233027, 0.6656817877291767, 0.3089819874998143, 0.20985555587709392, 0.14153091040714694, 0.6401141192024565, 0.457183891176168, 0.19455325793863953, 0.9730240010979829, 0.8225868519467548, 0.805763741683404, 0.8726857715345905, 0.7137409246627059, 0.6115355738997259, 0.9409888811746385, 0.7565867664554959, 0.09739353929248173, 0.5561759455727607, 0.7517833265733507, 0.6116776532802752, 0.2148955427568604, 0.4922051012286932, 0.30409240403653615, 0.07851416866043659, 0.3667865586221415, 0.8395749353539559, 0.32051751426093733, 0.6897681392115821, 0.9013012776520165, 0.9368713781503238, 0.5890964362959592, 0.4708435666635403, 0.27938713990716024, 0.4931079083849914, 0.8514069626139279, 0.7928682891764082, 0.5740248441100194, 0.39418084695245814, 0.3306153272510999, 0.19396927086017735, 0.8676325335706393, 0.6675172523953704, 0.3791275879238931, 0.7131045996424354, 0.5049551756770642, 0.2712318924697933, 0.3770401445503363, 0.21146202520583213, 0.8138971343988545, 0.7621531768728442, 0.6296487323184055, 0.5339645634552871, 0.6183883307119407, 0.9630575743187855, 0.9630575743187855, 0.33770342083325244, 0.37004360988386886, 0.21412650458560256, 0.9139736412586813, 0.5471753477411291, 0.1945833200871293, 0.6010385166981232, 0.5249703130613139, 0.13454934663111895, 0.13454934663111895, 0.8403654141456329, 0.7341179235194267, 0.7484894468005275, 0.2863195711013584, 0.3638907697980561, 0.1684117235737148, 0.2879810238271111, 0.07484600597803637, 0.5344515362836336, 0.5344515362836336, 0.656967204400338, 0.761790298947744, 0.358494154026733, 0.6829299928208146, 0.24806369920997795, 0.6886912670837468, 0.6461702544628923, 0.35352434024087065, 0.5030925984270136, 0.5157218360142725, 0.1273729965772602, 0.7186674549242368, 0.02029515808221871, 0.6922689077179544, 0.39019149792244645, 0.9970990319627566, 0.9576098088601497, 0.8799301909994293, 0.5236313332489478, 0.40255694111759566, 0.8342908963340514, 0.3873018899260485, 0.6881674287878089, 0.04854959789223989, 0.4727357561542518, 0.24938193202659553, 0.6144247719617756, 0.45811161125516264, 0.36147917096227966, 0.6158177884622144, 0.6621985275666261, 0.27940989585115406, 0.4381571926581992, 0.7599299973142043, 0.806468478086475, 0.771246570656298, 0.3521792469628421, 0.6144247719617756, 0.5886804020760216, 0.40552118795760006, 0.7897338461698741, 0.2970896913425429, 0.24061063809614525, 0.0925777641229718, 0.8291118609819546, 0.27300086144555935, 0.8286757414493822, 0.2612683300578883, 0.13257474647980072, 0.49552488195292543, 0.9216980524954733, 0.7033428616939958, 0.8607707427913157, 0.9711126269739102, 0.316283428689061, 0.12306306362645547, 0.8634739287043888, 0.5698107453801807], "total had os dependency": 6, "total were dependent on another vuln": 6}, "MTD Statistics": [{"record name": "CompleteTopologyShuffle", "x": [1006, 3438, 6958, 11649, 12929, 15959, 20842, 25379, 28663, 33159, 35012, 36959, 41491, 42865, 45084, 46307, 48657, 51163, 54157, 55860, 58118, 61950, 66785, 70031, 73791, 75960, 77238, 78600, 80177, 82665, 86509, 90039, 92464, 97369, 100944, 104708, 109039, 111808, 113463, 117551, 122447, 125743, 126893, 130527, 134180, 137796, 139490, 144446, 147127, 151226, 152511, 157141, 160364, 165155, 167005, 170897, 173335, 175631, 178945, 181392, 182534, 185483, 187378, 188941, 193829, 194847, 198842, 200071, 203279, 206511, 208728, 213643, 215775, 219591, 221588, 225093, 227085, 229260, 230870, 232616, 235566, 237609, 239575, 242920, 246869], "y": [1, 1, 1, 1, 1, 1, 1, 1, 1, 1, 1, 1, 1, 1, 1, 1, 1, 1, 1, 1, 1, 1, 1, 1, 1, 1, 1, 1, 1, 1, 1, 1, 1, 1, 1, 1, 1, 1, 1, 1, 1, 1, 1, 1, 1, 1, 1, 1, 1, 1, 1, 1, 1, 1, 1, 1, 1, 1, 1, 1, 1, 1, 1, 1, 1, 1, 1, 1, 1, 1, 1, 1, 1, 1, 1, 1, 1, 1, 1, 1, 1, 1, 1, 1, 1], "cumulative y": [0, 1, 2, 3, 4, 5, 6, 7, 8, 9, 10, 11, 12, 13, 14, 15, 16, 17, 18, 19, 20, 21, 22, 23, 24, 25, 26, 27, 28, 29, 30, 31, 32, 33, 34, 35, 36, 37, 38, 39, 40, 41, 42, 43, 44, 45, 46, 47, 48, 49, 50, 51, 52, 53, 54, 55, 56, 57, 58, 59, 60, 61, 62, 63, 64, 65, 66, 67, 68, 69, 70, 71, 72, 73, 74, 75, 76, 77, 78, 79, 80, 81, 82, 83, 84], "total events": 85, "blocked times": [11649, 15959, 20842, 35012, 36959, 54157, 55860, 58118, 61950, 66785, 70031, 73791, 75960, 77238, 78600, 80177, 82665, 86509, 90039, 92464, 97369, 100944, 104708, 109039, 111808, 113463, 117551, 122447, 125743, 126893, 130527, 134180, 137796, 139490, 144446, 147127, 151226, 152511, 157141, 160364, 167005, 170897, 173335, 175631, 178945, 181392, 182534, 185483, 187378, 188941, 193829, 194847, 198842, 200071, 203279, 206511, 208728, 213643, 215775, 219591, 221588, 225093, 227085, 229260, 230870, 232616, 235566, 239575, 242920, 246869], "total blocks": 70, "blocked values": ["CompleteTopologyShuffle", "CompleteTopologyShuffle", "CompleteTopologyShuffle", "CompleteTopologyShuffle", "CompleteTopologyShuffle", "CompleteTopologyShuffle", "CompleteTopologyShuffle", "CompleteTopologyShuffle", "CompleteTopologyShuffle", "CompleteTopologyShuffle", "CompleteTopologyShuffle", "CompleteTopologyShuffle", "CompleteTopologyShuffle", "CompleteTopologyShuffle", "CompleteTopologyShuffle", "CompleteTopologyShuffle", "CompleteTopologyShuffle", "CompleteTopologyShuffle", "CompleteTopologyShuffle", "CompleteTopologyShuffle", "CompleteTopologyShuffle", "CompleteTopologyShuffle", "CompleteTopologyShuffle", "CompleteTopologyShuffle", "CompleteTopologyShuffle", "CompleteTopologyShuffle", "CompleteTopologyShuffle", "CompleteTopologyShuffle", "CompleteTopologyShuffle", "CompleteTopologyShuffle", "CompleteTopologyShuffle", "CompleteTopologyShuffle", "CompleteTopologyShuffle", "CompleteTopologyShuffle", "CompleteTopologyShuffle", "CompleteTopologyShuffle", "CompleteTopologyShuffle", "CompleteTopologyShuffle", "CompleteTopologyShuffle", "CompleteTopologyShuffle", "CompleteTopologyShuffle", "CompleteTopologyShuffle", "CompleteTopologyShuffle", "CompleteTopologyShuffle", "CompleteTopologyShuffle", "CompleteTopologyShuffle", "CompleteTopologyShuffle", "CompleteTopologyShuffle", "CompleteTopologyShuffle", "CompleteTopologyShuffle", "CompleteTopologyShuffle", "CompleteTopologyShuffle", "CompleteTopologyShuffle", "CompleteTopologyShuffle", "CompleteTopologyShuffle", "CompleteTopologyShuffle", "CompleteTopologyShuffle", "CompleteTopologyShuffle", "CompleteTopologyShuffle", "CompleteTopologyShuffle", "CompleteTopologyShuffle", "CompleteTopologyShuffle", "CompleteTopologyShuffle", "CompleteTopologyShuffle", "CompleteTopologyShuffle", "CompleteTopologyShuffle", "CompleteTopologyShuffle", "CompleteTopologyShuffle", "CompleteTopologyShuffle", "CompleteTopologyShuffle"], "cumulative blocked": [0, 1, 2, 3, 4, 5, 6, 7, 8, 9, 10, 11, 12, 13, 14, 15, 16, 17, 18, 19, 20, 21, 22, 23, 24, 25, 26, 27, 28, 29, 30, 31, 32, 33, 34, 35, 36, 37, 38, 39, 40, 41, 42, 43, 44, 45, 46, 47, 48, 49, 50, 51, 52, 53, 54, 55, 56, 57, 58, 59, 60, 61, 62, 63, 64, 65, 66, 67, 68, 69]}], "Total MTD Events": 85, "Total MTD Blocking Hacker Events": 70, "Complete Time": 249999, "Simulation Type": "CompleteTopologyShuffle"}