{"Total Initial Vulnerabilities": 761, "Initial Vulns Per OS": {"ubuntu": {"18.04": 16, "20.04": 38, "16.04": 50, "12.04": 55, "14.04": 35, "10.04": 32}, "centos": {"7": 38, "8": 7, "6": 24, "3": 15, "5": 15, "4": 3}, "freebsd": {"11": 42, "9": 16, "12": 34, "10": 35, "13": 14, "8": 98}, "windows": {"8": 66, "8.1": 26, "10": 25, "7": 27, "vista": 7, "xp": 43}}, "Average Initial RoA Per OS": {"ubuntu": {"18.04": 0.037020856240400135, "20.04": 0.043335028250039424, "16.04": 0.041003448633428176, "12.04": 0.031508498854934563, "14.04": 0.054535763680277675, "10.04": 0.06106201370960693}, "centos": {"7": 0.057725854721664756, "8": 0.05781693490941953, "6": 0.03264307824924476, "3": 0.0778192991198463, "5": 0.03866161611927829, "4": 0.00938285589158752}, "freebsd": {"11": 0.02889134164549668, "9": 0.04836856468359643, "12": 0.04143641544158865, "10": 0.07177641958480357, "13": 0.03415839697119936, "8": 0.05554545123663208}, "windows": {"8": 0.03295153145323353, "8.1": 0.052287794792015424, "10": 0.034332719486354614, "7": 0.03481623176031955, "vista": 0.032812123795247575, "xp": 0.04028297532685677}}, "OS Types In Initial Network": {"ubuntu 18.04": 11, "centos 7": 21, "ubuntu 20.04": 19, "freebsd 11": 10, "windows 8": 17, "freebsd 9": 4, "freebsd 12": 16, "windows 8.1": 10, "ubuntu 16.04": 12, "ubuntu 12.04": 8, "ubuntu 14.04": 10, "freebsd 10": 7, "windows 10": 12, "freebsd 13": 10, "windows 7": 4, "centos 8": 11, "windows vista": 1, "centos 6": 6, "centos 3": 1, "centos 5": 4, "ubuntu 10.04": 1, "freebsd 8": 3, "centos 4": 1, "windows xp": 1}, "Initial Hosts Without Vulnerabilities": 33, "Host Compromises": {"record name": "Host Compromises", "x": [2004, 3280, 4551, 4582, 5661, 5812, 5861, 6022, 6168, 7401, 8550, 9092, 9248, 12890, 13244, 14946, 15031, 15361, 16229, 16308, 16688, 19952, 22026, 26036, 26717, 27094, 30209, 30431, 33324, 33409, 34402, 34489, 34883, 38843, 39648, 47584, 49535, 52943, 53376, 65332, 85910, 87683, 99148, 105894, 106826, 106936, 112047, 126032, 143112, 150211, 152842, 155341, 158314, 168223, 170983, 187136, 191900, 198996, 220863, 221270, 221370, 225258, 233339], "y": ["windows 8.1", "freebsd 12", "centos 7", "windows 8", "centos 7", "ubuntu 12.04", "windows 10", "windows 8.1", "freebsd 10", "centos 7", "centos 8", "freebsd 12", "ubuntu 14.04", "windows 8", "centos 7", "centos 7", "freebsd 13", "ubuntu 16.04", "freebsd 11", "windows 8", "windows 8", "centos 8", "freebsd 12", "ubuntu 12.04", "ubuntu 16.04", "ubuntu 20.04", "freebsd 8", "centos 6", "ubuntu 16.04", "freebsd 11", "centos 7", "centos 7", "windows 8.1", "windows vista", "windows 8", "windows 8.1", "centos 6", "freebsd 13", "windows 10", "windows 8", "ubuntu 20.04", "windows 7", "centos 3", "ubuntu 12.04", "freebsd 12", "ubuntu 16.04", "windows 8", "ubuntu 14.04", "ubuntu 16.04", "centos 5", "windows 8", "freebsd 11", "ubuntu 20.04", "windows 10", "freebsd 12", "freebsd 12", "freebsd 11", "freebsd 12", "centos 8", "windows 10", "centos 8", "ubuntu 10.04", "ubuntu 20.04"], "cumulative y": [0, 1, 2, 3, 4, 5, 6, 7, 8, 9, 10, 11, 12, 13, 14, 15, 16, 17, 18, 19, 20, 21, 22, 23, 24, 25, 26, 27, 28, 29, 30, 31, 32, 33, 34, 35, 36, 37, 38, 39, 40, 41, 42, 43, 44, 45, 46, 47, 48, 49, 50, 51, 52, 53, 54, 55, 56, 57, 58, 59, 60, 61, 62], "total events": 63}, "Vuln Compromises": {"record name": "Vuln Compromises", "x": [2004, 3280, 5861, 6022, 6168, 9248, 12890, 13244, 14946, 16308, 16688, 19952, 22026, 26036, 26717, 27094, 30209, 30431, 33324, 34402, 34883, 39648, 47584, 65332, 87683, 99148, 105894, 112047, 143112], "y": ["windows 8.1", "freebsd 12", "windows 10", "windows 8.1", "freebsd 10", "ubuntu 14.04", "windows 8", "centos 7", "centos 7", "windows 8", "windows 8", "centos 8", "freebsd 12", "ubuntu 12.04", "ubuntu 16.04", "ubuntu 20.04", "freebsd 8", "centos 6", "ubuntu 16.04", "centos 7", "windows 8.1", "windows 8", "windows 8.1", "windows 8", "windows 7", "centos 3", "ubuntu 12.04", "windows 8", "ubuntu 16.04"], "cumulative y": [0, 1, 2, 3, 4, 5, 6, 7, 8, 9, 10, 11, 12, 13, 14, 15, 16, 17, 18, 19, 20, 21, 22, 23, 24, 25, 26, 27, 28], "total events": 29}, "Reuse Password Compromises": {"record name": "Reuse Password Compromises", "x": [4551, 4582, 5661, 5812, 8550, 9092, 15031, 15361, 16229, 33409, 34489, 38843, 49535, 52943, 53376, 85910, 106826, 106936, 126032, 152842, 155341, 158314, 168223, 170983, 187136, 191900, 198996, 221370, 225258, 233339], "y": ["centos 7", "windows 8", "centos 7", "ubuntu 12.04", "centos 8", "freebsd 12", "freebsd 13", "ubuntu 16.04", "freebsd 11", "freebsd 11", "centos 7", "windows vista", "centos 6", "freebsd 13", "windows 10", "ubuntu 20.04", "freebsd 12", "ubuntu 16.04", "ubuntu 14.04", "windows 8", "freebsd 11", "ubuntu 20.04", "windows 10", "freebsd 12", "freebsd 12", "freebsd 11", "freebsd 12", "centos 8", "ubuntu 10.04", "ubuntu 20.04"], "cumulative y": [0, 1, 2, 3, 4, 5, 6, 7, 8, 9, 10, 11, 12, 13, 14, 15, 16, 17, 18, 19, 20, 21, 22, 23, 24, 25, 26, 27, 28, 29], "total events": 30}, "Password Spray Compromises": {"record name": "Password Spray Compromises", "x": [7401, 150211, 220863, 221270], "y": ["centos 7", "centos 5", "centos 8", "windows 10"], "cumulative y": [0, 1, 2, 3], "total events": 4}, "User Account Leaks": {"record name": "User Account Has Been Leaked By Compromise", "x": [2004, 2004, 2004, 3280, 3280, 3280, 4551, 4551, 4582, 5661, 5661, 5812, 5861, 5861, 6022, 6168, 6168, 7401, 7401, 8550, 9092, 9248, 12890, 12890, 12890, 13244, 14946, 14946, 14946, 15031, 15031, 16229, 16308, 16688, 16688, 16688, 19952, 26036, 26036, 26717, 27094, 30209, 30431, 30431, 33409, 34883, 34883, 38843, 39648, 65332, 65332, 99148, 126032, 143112, 150211, 150211, 187136, 221270, 221270, 221370], "y": ["Caron", "Zarah", "Kath", "Batsheva", "Tiphany", "Adele", "Johnath", "Bethina", "Ardra", "Eva", "Katti", "Gretchen", "Marinna", "Patricia", "Mirabel", "Jen", "Margit", "Melisande", "Bobbe", "Brunhilde", "Jobie", "Clarabelle", "Aretha", "Gussie", "Ronny", "Clari", "Juline", "Ag", "Halimeda", "Julissa", "Tabina", "Jo", "Holly", "Brittani", "Coralyn", "Lydie", "Freddi", "Anna-Diana", "Myrtice", "Cordi", "Barby", "Micki", "Kit", "Carlynne", "Cookie", "Lois", "Carie", "Renata", "Carmella", "Aurel", "Michaela", "Idette", "Binny", "Helen", "Inga", "Erinna", "Shell", "Calypso", "Prudi", "Kacy"], "cumulative y": [0, 1, 2, 3, 4, 5, 6, 7, 8, 9, 10, 11, 12, 13, 14, 15, 16, 17, 18, 19, 20, 21, 22, 23, 24, 25, 26, 27, 28, 29, 30, 31, 32, 33, 34, 35, 36, 37, 38, 39, 40, 41, 42, 43, 44, 45, 46, 47, 48, 49, 50, 51, 52, 53, 54, 55, 56, 57, 58, 59], "total events": 60}, "Vulnerabilities Exploited": {"record name": "Vulnerabilities Exploited", "x": [398, 865, 865, 865, 1083, 1083, 1434, 1491, 1491, 1748, 2004, 2176, 2176, 2842, 2842, 3008, 3079, 3079, 3138, 3208, 3280, 3882, 3987, 4483, 4483, 4483, 5562, 5562, 5861, 6168, 6168, 6644, 7316, 7316, 7619, 7991, 7991, 8145, 8424, 8660, 8660, 9248, 11135, 11135, 11135, 11135, 11135, 12704, 12704, 13033, 14399, 14399, 15758, 16308, 16688, 16688, 16688, 16831, 18740, 19694, 19952, 20225, 20225, 20225, 21595, 21595, 21595, 21595, 21595, 21595, 22026, 22138, 26036, 28773, 30209, 30209, 30209, 30209, 30209, 30209, 30209, 30209, 30209, 30209, 30209, 30209, 30209, 30431, 31273, 33324, 33324, 34402, 35515, 35515, 35515, 35515, 35515, 35515, 39648, 46197, 46800, 47697, 54567, 54567, 55566, 73339, 77622, 79446, 79808, 87683, 96514, 99148, 99148, 99148, 99307, 102828, 102828, 105894, 105894, 106369, 107633, 116442, 126610, 144339, 166033, 166033, 187650, 187650, 214751, 214751, 217307, 249689], "cumulative exploited vulns": [0, 1, 2, 3, 4, 5, 6, 7, 8, 9, 10, 11, 12, 13, 14, 15, 16, 17, 18, 19, 20, 21, 22, 23, 24, 25, 26, 27, 28, 29, 30, 31, 32, 33, 34, 35, 36, 37, 38, 39, 40, 41, 42, 43, 44, 45, 46, 47, 48, 49, 50, 51, 52, 53, 54, 55, 56, 57, 58, 59, 60, 61, 62, 63, 64, 65, 66, 67, 68, 69, 70, 71, 72, 73, 74, 75, 76, 77, 78, 79, 80, 81, 82, 83, 84, 85, 86, 87, 88, 89, 90, 91, 92, 93, 94, 95, 96, 97, 98, 99, 100, 101, 102, 103, 104, 105, 106, 107, 108, 109, 110, 111, 112, 113, 114, 115, 116, 117, 118, 119, 120, 121, 122, 123, 124, 125, 126, 127, 128, 129, 130, 131], "roa": [0.23701754027459326, 0.2464976453954426, 0.026943264605314505, 0.026943264605314505, 0.6550104954685738, 0.021387690370634274, 0.35227561993332906, 0.37018089285467637, 0.040084264593585675, 0.5749605842019031, 0.5885048444280234, 0.13955823863491237, 0.13955823863491237, 0.2685490971513425, 0.3662211306595753, 0.03193632886082008, 0.6910923386725601, 0.02426854545834471, 0.22862998179956312, 0.4867960936701679, 0.17459358229837113, 0.09927201468279019, 0.6170624183208013, 0.49779987370709333, 0.09560531541406735, 0.12136429314208586, 0.4453937908582321, 0.17950284915487075, 0.4695677412950755, 0.5979124272461591, 0.10885851967996188, 0.3734085131807611, 0.5502902865845425, 0.7208133538391113, 0.3679442911425932, 0.39060640210467923, 0.19846540296994655, 0.40451933836133247, 0.19359476306564846, 0.2545374538336054, 0.14250612788489755, 0.5969465206344455, 0.5001653557228148, 0.037316865771271246, 0.029002693465934516, 0.037316865771271246, 0.002334965231556814, 0.4627592442805491, 0.39545835503627685, 0.034524386887438266, 0.21931404550668013, 0.2345187675464706, 0.11931120102351156, 0.04488121606287824, 0.5953696730969893, 0.2924871367790503, 0.13043843452457465, 0.4203719839439066, 0.15884764575942711, 0.48685013530541676, 0.14116784825052214, 0.5881094062026891, 0.11135261857175535, 0.11135261857175535, 0.8226004844609209, 0.7457181550981128, 0.5304562665646627, 0.2407751280290944, 0.5181296933345112, 0.19847513627374422, 0.24764792299970811, 0.2462987360599896, 0.6569198399821677, 0.30186582179441745, 0.3062695492709723, 0.2779518749613684, 0.0736272447718853, 0.2485986255959761, 0.039135922138354755, 0.5996309190849345, 0.3206176211704294, 0.16000560717080417, 0.2302381495435697, 0.42267691224821824, 0.42267691224821824, 0.2613862055783286, 0.15330511086723905, 0.5239996438511197, 0.31047924168141894, 0.6494385375231253, 0.6681223996062975, 0.4413675737556152, 0.34622959279762794, 0.389587443924724, 0.20338895114307287, 0.0512662569675579, 0.389587443924724, 0.20338895114307287, 0.05106268668594762, 0.23998783690632103, 0.16755066789380446, 0.09701165501698217, 0.294848865652911, 0.294848865652911, 0.06917515710456723, 0.001959463503057633, 0.15854625786335946, 0.018854558400065856, 0.24383173976832398, 0.3924952717491961, 0.15847401681294718, 0.20143342871185585, 0.14062100787389545, 0.053489937993263806, 0.08535455731000771, 0.03726724497559806, 0.008598637093549804, 0.13333287421577775, 0.13333287421577775, 0.04958125043136131, 0.0463962245949786, 0.8103089460381161, 0.013580043026352762, 0.2491746666241048, 0.32997898740711357, 0.13179825326359512, 0.02076605519953596, 0.02076605519953596, 0.5929744659463283, 0.3731647788213016, 0.7986725260457749, 0.19601991744222963], "impact": [3.6812902667045733, 2.776790768794586, 0.5172422152669887, 0.5172422152669887, 8.383428340506784, 0.3323531074698294, 4.806245140766694, 5.3819804612336135, 2.6780244023226683, 7.150725070198936, 6.170600618401764, 2.2761812836019657, 2.2761812836019657, 3.1382250967124428, 4.9167371133885265, 6.3417209012765845, 9.391749089475391, 5.094725703583835, 2.710585483685728, 6.9597622609078815, 8.707283428068708, 1.138369011213991, 7.017178363241172, 5.383745439234572, 2.6677331821763026, 7.225305894376673, 5.773118357476518, 4.640119787566848, 7.406856056355071, 6.83992059284964, 1.3017461877504621, 7.502610473709889, 6.177388726952177, 8.848309498596556, 9.894904822744806, 8.23521236670057, 7.241505912274036, 5.435971622477713, 2.229891602498398, 3.9867164075762194, 2.348395013858396, 8.808430987983037, 6.343179609946708, 3.691897757032848, 0.3275833464749289, 3.691897757032848, 0.0785877358060838, 6.755467317946527, 6.763091779295224, 1.2178538698519326, 2.3791894739503503, 5.88262661745104, 6.470489814067818, 2.0483869988192085, 8.63041159317325, 3.5421512507126485, 3.4042137269393544, 7.68774135982103, 3.401608440762814, 6.881596426487281, 1.5225788416046038, 7.388896822388742, 6.8668500040775315, 6.8668500040775315, 9.299465809287316, 9.981681025309436, 6.7511063878684405, 3.545652256450851, 7.632093840785039, 2.432702782444891, 9.98643320336653, 4.099637354881529, 8.91637755093576, 6.231244778935898, 3.121838814704806, 6.374546944404466, 1.5718521123520268, 4.413102887013478, 1.276503061363241, 9.814290978739383, 4.172855752859295, 1.9967273153951504, 3.6541725963556804, 5.925647594218075, 5.925647594218075, 4.127321101263352, 3.5210303935543896, 8.35946997903985, 8.951045163992132, 8.975543306224235, 9.704827424835003, 7.892442074534958, 8.815786583525332, 5.173560394809389, 3.791414461939886, 0.9000307247780326, 5.173560394809389, 3.791414461939886, 7.734864584019876, 7.5069941939453875, 4.506950675138849, 2.282750560283695, 4.006650236756474, 4.006650236756474, 1.6808345678808745, 0.023971767550102774, 2.894108204051519, 0.45517768732325936, 4.683009399596008, 9.625137748439972, 5.284807937979213, 3.1257318296277656, 2.1360088881542625, 2.0360542798832, 6.010144098529867, 1.054982677385704, 0.45821230943981606, 6.7268383266463765, 6.7268383266463765, 0.5078705550698004, 4.960281792114982, 9.494461949067423, 1.3039469073313736, 4.570921078769402, 3.5537635806828973, 4.175303512444096, 2.4221432481886387, 2.4221432481886387, 7.650240762648176, 5.074951024163859, 8.947772165534708, 5.579153741981617], "complexity": [0.6438436610617159, 0.8877069463265612, 0.5209022738294283, 0.5209022738294283, 0.7813157921368693, 0.6435231050931522, 0.7329539164478279, 0.6878153785973176, 0.14967848895932512, 0.8040591388390597, 0.9537237634096809, 0.6131244450532826, 0.6131244450532826, 0.8557356112940097, 0.7448458646738229, 0.05035908920935217, 0.7358505131349963, 0.04763464584810373, 0.8434708411729658, 0.6994435663477199, 0.20051441272205872, 0.8720547880772291, 0.879359746010198, 0.9246348649386876, 0.35837660247594083, 0.16797114878768182, 0.7714960326102127, 0.3868496016759023, 0.633963638178424, 0.8741511237297238, 0.8362499595107665, 0.49770478487352177, 0.890813757896772, 0.8146339749456555, 0.3718522792627802, 0.4743124824371413, 0.2740664792299021, 0.7441527779296109, 0.8681801521147597, 0.6384639081673608, 0.6068234987893327, 0.6776990379431183, 0.7885088969237258, 0.10107773353198857, 0.8853531102245513, 0.10107773353198857, 0.2971157277413322, 0.6850144075912944, 0.5847301322258371, 0.2834854635855102, 0.9218015122710519, 0.398663357029599, 0.18439284266256173, 0.21910515976107048, 0.6898508450836033, 0.8257330533816266, 0.3831675828469462, 0.5468081771597124, 0.4669780444330194, 0.7074668509061784, 0.9271628134655362, 0.7959366876266116, 0.16215967802651032, 0.16215967802651032, 0.8845674593904042, 0.7470867414088652, 0.7857323468015237, 0.6790714672907799, 0.678882760279604, 0.8158626598612868, 0.24798435833549004, 0.6007817637009191, 0.7367564195542897, 0.48443903666703125, 0.9810549725640861, 0.4360339289764783, 0.46841076328557296, 0.5633193513967961, 0.30658698222438696, 0.6109773190787904, 0.7683410119095012, 0.8013393012512537, 0.6300691701677885, 0.7133007920697874, 0.7133007920697874, 0.6333071722922639, 0.43539843094759967, 0.6268335733784227, 0.346863674568866, 0.7235645970007872, 0.688443359535223, 0.5592281445811202, 0.3927381743163464, 0.7530354614504847, 0.5364461025951999, 0.5696056318544157, 0.7530354614504847, 0.5364461025951999, 0.0660162645787522, 0.3196856567437848, 0.3717605981757114, 0.4249770286111584, 0.7358986890046126, 0.7358986890046126, 0.4115524420215867, 0.8174046819710766, 0.5478242231627949, 0.41422413543473346, 0.5206731803471476, 0.4077814593487882, 0.2998671260578373, 0.6444360543106604, 0.6583353124312459, 0.2627137130957643, 0.14201748894986754, 0.3532498284042731, 0.1876561785095211, 0.1982103147739096, 0.1982103147739096, 0.9762576297526638, 0.09353546136981872, 0.8534543088223207, 0.10414567456696033, 0.5451301003236495, 0.9285338765943013, 0.3156614911246163, 0.08573421582338503, 0.08573421582338503, 0.7751056265333364, 0.7353071528070236, 0.8925937219569863, 0.3513434590755816], "total had os dependency": 2, "total were dependent on another vuln": 4}, "MTD Statistics": [{"record name": "CompleteTopologyShuffle", "x": [3452, 7216, 9996, 11442, 13545, 17804, 18911, 23593, 25413, 27916, 32269, 33526, 35644, 40199, 42954, 46298, 49047, 52115, 56620, 59234, 63123, 64229, 65528, 67697, 72607, 75113, 77080, 80091, 82813, 86809, 89255, 91825, 92851, 97532, 99797, 103270, 106460, 109365, 113910, 118646, 120872, 122737, 126213, 128026, 129641, 133303, 138028, 142402, 146694, 147737, 149542, 151434, 156106, 158036, 159412, 163489, 167937, 170681, 172636, 173736, 174984, 179978, 182892, 184675, 186063, 190863, 192082, 194306, 196390, 199042, 200124, 203684, 206922, 211565, 213472, 217872, 221688, 223412, 224472, 226152, 229458, 233057, 236362, 239801, 241705, 242780, 245389, 246912, 248525], "y": [1, 1, 1, 1, 1, 1, 1, 1, 1, 1, 1, 1, 1, 1, 1, 1, 1, 1, 1, 1, 1, 1, 1, 1, 1, 1, 1, 1, 1, 1, 1, 1, 1, 1, 1, 1, 1, 1, 1, 1, 1, 1, 1, 1, 1, 1, 1, 1, 1, 1, 1, 1, 1, 1, 1, 1, 1, 1, 1, 1, 1, 1, 1, 1, 1, 1, 1, 1, 1, 1, 1, 1, 1, 1, 1, 1, 1, 1, 1, 1, 1, 1, 1, 1, 1, 1, 1, 1, 1], "cumulative y": [0, 1, 2, 3, 4, 5, 6, 7, 8, 9, 10, 11, 12, 13, 14, 15, 16, 17, 18, 19, 20, 21, 22, 23, 24, 25, 26, 27, 28, 29, 30, 31, 32, 33, 34, 35, 36, 37, 38, 39, 40, 41, 42, 43, 44, 45, 46, 47, 48, 49, 50, 51, 52, 53, 54, 55, 56, 57, 58, 59, 60, 61, 62, 63, 64, 65, 66, 67, 68, 69, 70, 71, 72, 73, 74, 75, 76, 77, 78, 79, 80, 81, 82, 83, 84, 85, 86, 87, 88], "total events": 89, "blocked times": [9996, 11442, 13545, 17804, 18911, 23593, 25413, 27916, 32269, 33526, 35644, 40199, 42954, 46298, 49047, 52115, 56620, 59234, 63123, 64229, 65528, 67697, 72607, 75113, 77080, 80091, 82813, 86809, 89255, 91825, 92851, 97532, 99797, 103270, 106460, 109365, 113910, 118646, 120872, 122737, 126213, 128026, 129641, 133303, 138028, 142402, 146694, 147737, 149542, 151434, 156106, 158036, 159412, 163489, 167937, 170681, 172636, 173736, 174984, 179978, 182892, 184675, 186063, 190863, 192082, 194306, 196390, 199042, 200124, 203684, 206922, 211565, 213472, 217872, 221688, 223412, 224472, 226152, 229458, 233057, 236362, 239801, 241705, 242780, 245389, 246912, 248525], "total blocks": 87, "blocked values": ["CompleteTopologyShuffle", "CompleteTopologyShuffle", "CompleteTopologyShuffle", "CompleteTopologyShuffle", "CompleteTopologyShuffle", "CompleteTopologyShuffle", "CompleteTopologyShuffle", "CompleteTopologyShuffle", "CompleteTopologyShuffle", "CompleteTopologyShuffle", "CompleteTopologyShuffle", "CompleteTopologyShuffle", "CompleteTopologyShuffle", "CompleteTopologyShuffle", "CompleteTopologyShuffle", "CompleteTopologyShuffle", "CompleteTopologyShuffle", "CompleteTopologyShuffle", "CompleteTopologyShuffle", "CompleteTopologyShuffle", "CompleteTopologyShuffle", "CompleteTopologyShuffle", "CompleteTopologyShuffle", "CompleteTopologyShuffle", "CompleteTopologyShuffle", "CompleteTopologyShuffle", "CompleteTopologyShuffle", "CompleteTopologyShuffle", "CompleteTopologyShuffle", "CompleteTopologyShuffle", "CompleteTopologyShuffle", "CompleteTopologyShuffle", "CompleteTopologyShuffle", "CompleteTopologyShuffle", "CompleteTopologyShuffle", "CompleteTopologyShuffle", "CompleteTopologyShuffle", "CompleteTopologyShuffle", "CompleteTopologyShuffle", "CompleteTopologyShuffle", "CompleteTopologyShuffle", "CompleteTopologyShuffle", "CompleteTopologyShuffle", "CompleteTopologyShuffle", "CompleteTopologyShuffle", "CompleteTopologyShuffle", "CompleteTopologyShuffle", "CompleteTopologyShuffle", "CompleteTopologyShuffle", "CompleteTopologyShuffle", "CompleteTopologyShuffle", "CompleteTopologyShuffle", "CompleteTopologyShuffle", "CompleteTopologyShuffle", "CompleteTopologyShuffle", "CompleteTopologyShuffle", "CompleteTopologyShuffle", "CompleteTopologyShuffle", "CompleteTopologyShuffle", "CompleteTopologyShuffle", "CompleteTopologyShuffle", "CompleteTopologyShuffle", "CompleteTopologyShuffle", "CompleteTopologyShuffle", "CompleteTopologyShuffle", "CompleteTopologyShuffle", "CompleteTopologyShuffle", "CompleteTopologyShuffle", "CompleteTopologyShuffle", "CompleteTopologyShuffle", "CompleteTopologyShuffle", "CompleteTopologyShuffle", "CompleteTopologyShuffle", "CompleteTopologyShuffle", "CompleteTopologyShuffle", "CompleteTopologyShuffle", "CompleteTopologyShuffle", "CompleteTopologyShuffle", "CompleteTopologyShuffle", "CompleteTopologyShuffle", "CompleteTopologyShuffle", "CompleteTopologyShuffle", "CompleteTopologyShuffle", "CompleteTopologyShuffle", "CompleteTopologyShuffle", "CompleteTopologyShuffle", "CompleteTopologyShuffle"], "cumulative blocked": [0, 1, 2, 3, 4, 5, 6, 7, 8, 9, 10, 11, 12, 13, 14, 15, 16, 17, 18, 19, 20, 21, 22, 23, 24, 25, 26, 27, 28, 29, 30, 31, 32, 33, 34, 35, 36, 37, 38, 39, 40, 41, 42, 43, 44, 45, 46, 47, 48, 49, 50, 51, 52, 53, 54, 55, 56, 57, 58, 59, 60, 61, 62, 63, 64, 65, 66, 67, 68, 69, 70, 71, 72, 73, 74, 75, 76, 77, 78, 79, 80, 81, 82, 83, 84, 85, 86]}], "Total MTD Events": 89, "Total MTD Blocking Hacker Events": 87, "Complete Time": 249999, "Simulation Type": "CompleteTopologyShuffle"}